deeva/__init__.py
deeva/app.py
deeva/caching.py
deeva/start.py
deeva/utils.py
deeva/animations/arrows.html
deeva/animations/astronaut.html
deeva/animations/planet.html
deeva/animations/slider.html
deeva/animations/static_planet.html
deeva/animations/supply.html
deeva/assets/backgrounds/main.png
deeva/assets/other/app.png
deeva/assets/other/astronaut.png
deeva/assets/other/disk.png
deeva/assets/other/hole.png
deeva/assets/other/no_image.png
deeva/assets/planets/blue.png
deeva/assets/planets/green.jpg
deeva/assets/planets/moon.jpg
deeva/assets/planets/purple.png
deeva/assets/planets/red.png
deeva/configs/__init__.py
deeva/configs/configs.py
deeva/configs/utils.py
deeva/front/__init__.py
deeva/front/elements.py
deeva/front/utils.py
deeva/loaders/__init__.py
deeva/loaders/converters.py
deeva/loaders/parsers.py
deeva/loaders/utils.py
deeva/src/__init__.py
deeva/src/core.py
deeva/src/utils.py
deeva/styles/background.html
deeva/styles/custom.html
deeva/styles/invisible_button.html
deeva/styles/stats_block.html
deeva/toy_data/labelmap.txt
deeva/toy_data/images/000000000009_jpg.rf.856f80d728927e943a5bccfdf49dd677.jpg
deeva/toy_data/images/000000000036_jpg.rf.af0418c203165d3ee53b7dee5fe8b301.jpg
deeva/toy_data/images/000000000042_jpg.rf.a1f5c146b4b81881b19f342a148c0f51.jpg
deeva/toy_data/images/000000000049_jpg.rf.bfa6e0ac33a75f530011d8b3b50a3b5c.jpg
deeva/toy_data/images/000000000061_jpg.rf.6945c178a14b90b01cd7d8b1e60e6a22.jpg
deeva/toy_data/images/000000000064_jpg.rf.01bec3a770d2bc9cc8eb02d41a0c7f79.jpg
deeva/toy_data/images/000000000071_jpg.rf.1e9a11ad22ba304c5519e32b3ab47a48.jpg
deeva/toy_data/images/000000000072_jpg.rf.244aee5e871d00c83983a224a5eb8ed5.jpg
deeva/toy_data/images/000000000073_jpg.rf.eb8e88e2239ba953b553f4e60b5d567c.jpg
deeva/toy_data/images/000000000074_jpg.rf.98fe5630d85530144d222acb65f55f15.jpg
deeva/toy_data/images/000000000077_jpg.rf.520601990c512b7983888cbedfe14ca1.jpg
deeva/toy_data/images/000000000078_jpg.rf.afbc984af561c845df5edc5f96c4037f.jpg
deeva-1.0.1.dist-info/AUTHORS.txt
deeva-1.0.1.dist-info/LICENSE
deeva-1.0.1.dist-info/METADATA
deeva-1.0.1.dist-info/WHEEL
deeva-1.0.1.dist-info/entry_points.txt
deeva-1.0.1.dist-info/top_level.txt
deeva-1.0.1.dist-info/RECORD
