Metadata-Version: 2.1
Name: deeva
Version: 1.0.1
Summary: Object Detection Data Analysis Toolbox
Home-page: https://github.com/vbyan/DEEVA
Author: Vahram Babajanyan, 
Author-email: vahram.babadjanyan@gmail.com
License: Apache License 2.0
Keywords: deeva,object-detection,analytics,visualization,datasets,toolkit,statistics,detection,streamlit,plotly
Classifier: Programming Language :: Python :: 3
Classifier: License :: OSI Approved :: Apache Software License
Classifier: Operating System :: POSIX :: Linux
Classifier: Operating System :: MacOS
Requires-Python: >=3.9
License-File: LICENSE
License-File: AUTHORS.txt
